UniversalClassifier/__init__.py
UniversalClassifier-0.0.4.dist-info/LICENSE
UniversalClassifier-0.0.4.dist-info/METADATA
UniversalClassifier-0.0.4.dist-info/WHEEL
UniversalClassifier-0.0.4.dist-info/top_level.txt
UniversalClassifier-0.0.4.dist-info/RECORD
