Metadata-Version: 2.1
Name: UniversalClassifier
Version: 0.0.4
Summary: A python library for classifying images.
Home-page: https://github.com/ParisNeo/TextPinner
Author: Saifeddine ALOUI
Author-email: aloui.saifeddine@gmail.com
License: UNKNOWN
Platform: UNKNOWN
Classifier: Programming Language :: Python :: 3.8
Classifier: License :: OSI Approved :: MIT License
Classifier: Operating System :: OS Independent
Requires-Dist: ftfy
Requires-Dist: regex
Requires-Dist: tqdm
Requires-Dist: torch
Requires-Dist: Pillow
Requires-Dist: torchvision
Requires-Dist: torchaudio
Provides-Extra: dev
